[
    {
        "url": "/wiki/Afghanistan",
        "alpha3": "AFG",
        "name": "Afghanistan",
        "flag_url": "//upload.wikimedia.org/wikipedia/commons/5/5c/Flag_of_the_Taliban.svg",
        "license": "Public domain",
        "continent": "Asia"
    },
    {
        "url": "/wiki/%C3%85land_Islands",
        "alpha3": "ALA",
        "name": "Aland Islands",
        "flag_url": "//upload.wikimedia.org/wikipedia/commons/5/52/Flag_of_%C3%85land.svg",
        "license": "Public domain",
        "continent": "Europe"
    },
    {
        "url": "/wiki/Albania",
        "alpha3": "ALB",
        "name": "Albania",
        "flag_url": "//upload.wikimedia.org/wikipedia/commons/3/36/Flag_of_Albania.svg",
        "license": "Public domain",
        "continent": "Europe"
    },
    {
        "url": "/wiki/Algeria",
        "alpha3": "DZA",
        "name": "Algeria",
        "flag_url": "//upload.wikimedia.org/wikipedia/commons/7/77/Flag_of_Algeria.svg",
        "license": "Public domain",
        "continent": "Africa"
    },
    {
        "url": "/wiki/American_Samoa",
        "alpha3": "ASM",
        "name": "American Samoa",
        "flag_url": "//upload.wikimedia.org/wikipedia/commons/8/87/Flag_of_American_Samoa.svg",
        "license": "Public domain",
        "continent": "Oceania"
    },
    {
        "url": "/wiki/Andorra",
        "alpha3": "AND",
        "name": "Andorra",
        "flag_url": "//upload.wikimedia.org/wikipedia/commons/1/19/Flag_of_Andorra.svg",
        "license": "Public domain",
        "continent": "Europe"
    },
    {
        "url": "/wiki/Angola",
        "alpha3": "AGO",
        "name": "Angola",
        "flag_url": "//upload.wikimedia.org/wikipedia/commons/9/9d/Flag_of_Angola.svg",
        "license": "Public domain",
        "continent": "Africa"
    },
    {
        "url": "/wiki/Anguilla",
        "alpha3": "AIA",
        "name": "Anguilla",
        "flag_url": "//upload.wikimedia.org/wikipedia/commons/b/b4/Flag_of_Anguilla.svg",
        "license": "Public domain",
        "continent": "North America"
    },
    {
        "url": "/wiki/Antigua_and_Barbuda",
        "alpha3": "ATG",
        "name": "Antigua and Barbuda",
        "flag_url": "//upload.wikimedia.org/wikipedia/commons/8/89/Flag_of_Antigua_and_Barbuda.svg",
        "license": "Public domain",
        "continent": "North America"
    },
    {
        "url": "/wiki/Argentina",
        "alpha3": "ARG",
        "name": "Argentina",
        "flag_url": "//upload.wikimedia.org/wikipedia/commons/1/1a/Flag_of_Argentina.svg",
        "license": "Public domain",
        "continent": "South America"
    },
    {
        "url": "/wiki/Armenia",
        "alpha3": "ARM",
        "name": "Armenia",
        "flag_url": "//upload.wikimedia.org/wikipedia/commons/2/2f/Flag_of_Armenia.svg",
        "license": "Public domain",
        "continent": "Europe"
    },
    {
        "url": "/wiki/Aruba",
        "alpha3": "ABW",
        "name": "Aruba",
        "flag_url": "//upload.wikimedia.org/wikipedia/commons/f/f6/Flag_of_Aruba.svg",
        "license": "Public domain",
        "continent": "South America"
    },
    {
        "url": "/wiki/Australia",
        "alpha3": "AUS",
        "name": "Australia",
        "flag_url": "//upload.wikimedia.org/wikipedia/commons/8/88/Flag_of_Australia_%28converted%29.svg",
        "license": "Public domain",
        "continent": "Oceania"
    },
    {
        "url": "/wiki/Austria",
        "alpha3": "AUT",
        "name": "Austria",
        "flag_url": "//upload.wikimedia.org/wikipedia/commons/4/41/Flag_of_Austria.svg",
        "license": "Public domain",
        "continent": "Europe"
    },
    {
        "url": "/wiki/Azerbaijan",
        "alpha3": "AZE",
        "name": "Azerbaijan",
        "flag_url": "//upload.wikimedia.org/wikipedia/commons/d/dd/Flag_of_Azerbaijan.svg",
        "license": "Public domain",
        "continent": "Europe"
    },
    {
        "url": "/wiki/Bahamas",
        "alpha3": "BHS",
        "name": "Bahamas",
        "flag_url": "//upload.wikimedia.org/wikipedia/commons/9/93/Flag_of_the_Bahamas.svg",
        "license": "Public domain",
        "continent": "North America"
    },
    {
        "url": "/wiki/Bahrain",
        "alpha3": "BHR",
        "name": "Bahrain",
        "flag_url": "//upload.wikimedia.org/wikipedia/commons/2/2c/Flag_of_Bahrain.svg",
        "license": "Public domain",
        "continent": "Asia"
    },
    {
        "url": "/wiki/Bangladesh",
        "alpha3": "BGD",
        "name": "Bangladesh",
        "flag_url": "//upload.wikimedia.org/wikipedia/commons/f/f9/Flag_of_Bangladesh.svg",
        "license": "Public domain",
        "continent": "Asia"
    },
    {
        "url": "/wiki/Barbados",
        "alpha3": "BRB",
        "name": "Barbados",
        "flag_url": "//upload.wikimedia.org/wikipedia/commons/e/ef/Flag_of_Barbados.svg",
        "license": "Public domain",
        "continent": "North America"
    },
    {
        "url": "/wiki/Belarus",
        "alpha3": "BLR",
        "name": "Belarus",
        "flag_url": "//upload.wikimedia.org/wikipedia/commons/8/85/Flag_of_Belarus.svg",
        "license": "Public domain",
        "continent": "Europe"
    },
    {
        "url": "/wiki/Belgium",
        "alpha3": "BEL",
        "name": "Belgium",
        "flag_url": "//upload.wikimedia.org/wikipedia/commons/6/65/Flag_of_Belgium.svg",
        "license": "Public domain",
        "continent": "Europe"
    },
    {
        "url": "/wiki/Belize",
        "alpha3": "BLZ",
        "name": "Belize",
        "flag_url": "//upload.wikimedia.org/wikipedia/commons/e/e7/Flag_of_Belize.svg",
        "license": "Public domain",
        "continent": "North America"
    },
    {
        "url": "/wiki/Benin",
        "alpha3": "BEN",
        "name": "Benin",
        "flag_url": "//upload.wikimedia.org/wikipedia/commons/0/0a/Flag_of_Benin.svg",
        "license": "Public domain",
        "continent": "Africa"
    },
    {
        "url": "/wiki/Bermuda",
        "alpha3": "BMU",
        "name": "Bermuda",
        "flag_url": "//upload.wikimedia.org/wikipedia/commons/b/bf/Flag_of_Bermuda.svg",
        "license": "Public domain",
        "continent": "North America"
    },
    {
        "url": "/wiki/Bhutan",
        "alpha3": "BTN",
        "name": "Bhutan",
        "flag_url": "//upload.wikimedia.org/wikipedia/commons/9/91/Flag_of_Bhutan.svg",
        "license": "Public domain",
        "continent": "Asia"
    },
    {
        "url": "/wiki/Bolivia",
        "alpha3": "BOL",
        "name": "Bolivia (Plurinational State of)",
        "flag_url": "//upload.wikimedia.org/wikipedia/commons/b/b3/Bandera_de_Bolivia_%28Estado%29.svg",
        "license": "Public domain",
        "continent": "South America"
    },
    {
        "url": "/wiki/Caribbean_Netherlands",
        "alpha3": "BES",
        "name": "Bonaire - Sint Eustatius and Saba",
        "flag_url": "//upload.wikimedia.org/wikipedia/commons/2/20/Flag_of_the_Netherlands.svg",
        "license": "Public domain",
        "continent": "South America"
    },
    {
        "url": "/wiki/Bosnia_and_Herzegovina",
        "alpha3": "BIH",
        "name": "Bosnia and Herzegovina",
        "flag_url": "//upload.wikimedia.org/wikipedia/commons/b/bf/Flag_of_Bosnia_and_Herzegovina.svg",
        "license": "Public domain",
        "continent": "Europe"
    },
    {
        "url": "/wiki/Botswana",
        "alpha3": "BWA",
        "name": "Botswana",
        "flag_url": "//upload.wikimedia.org/wikipedia/commons/f/fa/Flag_of_Botswana.svg",
        "license": "Public domain",
        "continent": "Africa"
    },
    {
        "url": "/wiki/Brazil",
        "alpha3": "BRA",
        "name": "Brazil",
        "flag_url": "//upload.wikimedia.org/wikipedia/en/0/05/Flag_of_Brazil.svg",
        "license": "Public domain",
        "continent": "South America"
    },
    {
        "url": "/wiki/British_Indian_Ocean_Territory",
        "alpha3": "IOT",
        "name": "British Indian Ocean Territory",
        "flag_url": "//upload.wikimedia.org/wikipedia/commons/6/65/Flag_of_the_Commissioner_of_the_British_Indian_Ocean_Territory.svg",
        "license": "Public domain",
        "continent": "Asia"
    },
    {
        "url": "/wiki/Brunei_Darussalam",
        "alpha3": "BRN",
        "name": "Brunei Darussalam",
        "flag_url": "//upload.wikimedia.org/wikipedia/commons/9/9c/Flag_of_Brunei.svg",
        "license": "Public domain",
        "continent": "Asia"
    },
    {
        "url": "/wiki/Bulgaria",
        "alpha3": "BGR",
        "name": "Bulgaria",
        "flag_url": "//upload.wikimedia.org/wikipedia/commons/9/9a/Flag_of_Bulgaria.svg",
        "license": "Public domain",
        "continent": "Europe"
    },
    {
        "url": "/wiki/Burkina_Faso",
        "alpha3": "BFA",
        "name": "Burkina Faso",
        "flag_url": "//upload.wikimedia.org/wikipedia/commons/3/31/Flag_of_Burkina_Faso.svg",
        "license": "Public domain",
        "continent": "Africa"
    },
    {
        "url": "/wiki/Burundi",
        "alpha3": "BDI",
        "name": "Burundi",
        "flag_url": "//upload.wikimedia.org/wikipedia/commons/5/50/Flag_of_Burundi.svg",
        "license": "Public domain",
        "continent": "Africa"
    },
    {
        "url": "/wiki/Cabo_Verde",
        "alpha3": "CPV",
        "name": "Cabo Verde",
        "flag_url": "//upload.wikimedia.org/wikipedia/commons/3/38/Flag_of_Cape_Verde.svg",
        "license": "Public domain",
        "continent": "Africa"
    },
    {
        "url": "/wiki/Cambodia",
        "alpha3": "KHM",
        "name": "Cambodia",
        "flag_url": "//upload.wikimedia.org/wikipedia/commons/8/83/Flag_of_Cambodia.svg",
        "license": "Public domain",
        "continent": "Asia"
    },
    {
        "url": "/wiki/Cameroon",
        "alpha3": "CMR",
        "name": "Cameroon",
        "flag_url": "//upload.wikimedia.org/wikipedia/commons/4/4f/Flag_of_Cameroon.svg",
        "license": "Public domain",
        "continent": "Africa"
    },
    {
        "url": "/wiki/Canada",
        "alpha3": "CAN",
        "name": "Canada",
        "flag_url": "//upload.wikimedia.org/wikipedia/commons/d/d9/Flag_of_Canada_%28Pantone%29.svg",
        "license": "Public domain",
        "continent": "North America"
    },
    {
        "url": "/wiki/Cayman_Islands",
        "alpha3": "CYM",
        "name": "Cayman Islands",
        "flag_url": "//upload.wikimedia.org/wikipedia/commons/0/0f/Flag_of_the_Cayman_Islands.svg",
        "license": "Public domain",
        "continent": "North America"
    },
    {
        "url": "/wiki/Central_African_Republic",
        "alpha3": "CAF",
        "name": "Central African Republic",
        "flag_url": "//upload.wikimedia.org/wikipedia/commons/6/6f/Flag_of_the_Central_African_Republic.svg",
        "license": "Public domain",
        "continent": "Africa"
    },
    {
        "url": "/wiki/Chad",
        "alpha3": "TCD",
        "name": "Chad",
        "flag_url": "//upload.wikimedia.org/wikipedia/commons/4/4b/Flag_of_Chad.svg",
        "license": "Public domain",
        "continent": "Africa"
    },
    {
        "url": "/wiki/Chile",
        "alpha3": "CHL",
        "name": "Chile",
        "flag_url": "//upload.wikimedia.org/wikipedia/commons/7/78/Flag_of_Chile.svg",
        "license": "Public domain",
        "continent": "South America"
    },
    {
        "url": "/wiki/China",
        "alpha3": "CHN",
        "name": "China",
        "flag_url": "//upload.wikimedia.org/wikipedia/commons/f/fa/Flag_of_the_People%27s_Republic_of_China.svg",
        "license": "Public domain",
        "continent": "Asia"
    },
    {
        "url": "/wiki/Christmas_Island",
        "alpha3": "CXR",
        "name": "Christmas Island",
        "flag_url": "//upload.wikimedia.org/wikipedia/commons/6/67/Flag_of_Christmas_Island.svg",
        "license": "Public domain",
        "continent": "Asia"
    },
    {
        "url": "/wiki/Cocos_(Keeling)_Islands",
        "alpha3": "CCK",
        "name": "Cocos (Keeling) Islands",
        "flag_url": "//upload.wikimedia.org/wikipedia/commons/7/74/Flag_of_the_Cocos_%28Keeling%29_Islands.svg",
        "license": "Public domain",
        "continent": "Asia"
    },
    {
        "url": "/wiki/Colombia",
        "alpha3": "COL",
        "name": "Colombia",
        "flag_url": "//upload.wikimedia.org/wikipedia/commons/2/21/Flag_of_Colombia.svg",
        "license": "Public domain",
        "continent": "South America"
    },
    {
        "url": "/wiki/Comoros",
        "alpha3": "COM",
        "name": "Comoros",
        "flag_url": "//upload.wikimedia.org/wikipedia/commons/9/94/Flag_of_the_Comoros.svg",
        "license": "Public domain",
        "continent": "Africa"
    },
    {
        "url": "/wiki/Republic_of_the_Congo",
        "alpha3": "COG",
        "name": "Congo",
        "flag_url": "//upload.wikimedia.org/wikipedia/commons/9/92/Flag_of_the_Republic_of_the_Congo.svg",
        "license": "Public domain",
        "continent": "Africa"
    },
    {
        "url": "/wiki/Democratic_Republic_of_the_Congo",
        "alpha3": "COD",
        "name": "Congo - Democratic Republic of the",
        "flag_url": "//upload.wikimedia.org/wikipedia/commons/6/6f/Flag_of_the_Democratic_Republic_of_the_Congo.svg",
        "license": "Public domain",
        "continent": "Africa"
    },
    {
        "url": "/wiki/Cook_Islands",
        "alpha3": "COK",
        "name": "Cook Islands",
        "flag_url": "//upload.wikimedia.org/wikipedia/commons/3/35/Flag_of_the_Cook_Islands.svg",
        "license": "Public domain",
        "continent": "Oceania"
    },
    {
        "url": "/wiki/Costa_Rica",
        "alpha3": "CRI",
        "name": "Costa Rica",
        "flag_url": "//upload.wikimedia.org/wikipedia/commons/f/f2/Flag_of_Costa_Rica.svg",
        "license": "Public domain",
        "continent": "North America"
    },
    {
        "url": "/wiki/Ivory_Coast",
        "alpha3": "CIV",
        "name": "C\u00f4te d'Ivoire",
        "flag_url": "//upload.wikimedia.org/wikipedia/commons/f/fe/Flag_of_C%C3%B4te_d%27Ivoire.svg",
        "license": "Public domain",
        "continent": "Africa"
    },
    {
        "url": "/wiki/Croatia",
        "alpha3": "HRV",
        "name": "Croatia",
        "flag_url": "//upload.wikimedia.org/wikipedia/commons/1/1b/Flag_of_Croatia.svg",
        "license": "Public domain",
        "continent": "Europe"
    },
    {
        "url": "/wiki/Cuba",
        "alpha3": "CUB",
        "name": "Cuba",
        "flag_url": "//upload.wikimedia.org/wikipedia/commons/b/bd/Flag_of_Cuba.svg",
        "license": "Public domain",
        "continent": "North America"
    },
    {
        "url": "/wiki/Cura%C3%A7ao",
        "alpha3": "CUW",
        "name": "Cura\u00e7ao",
        "flag_url": "//upload.wikimedia.org/wikipedia/commons/b/b1/Flag_of_Cura%C3%A7ao.svg",
        "license": "Public domain",
        "continent": "South America"
    },
    {
        "url": "/wiki/Cyprus",
        "alpha3": "CYP",
        "name": "Cyprus",
        "flag_url": "//upload.wikimedia.org/wikipedia/commons/d/d4/Flag_of_Cyprus.svg",
        "license": "Public domain",
        "continent": "Europe"
    },
    {
        "url": "/wiki/Czech_Republic",
        "alpha3": "CZE",
        "name": "Czechia",
        "flag_url": "//upload.wikimedia.org/wikipedia/commons/c/cb/Flag_of_the_Czech_Republic.svg",
        "license": "Public domain",
        "continent": "Europe"
    },
    {
        "url": "/wiki/Denmark",
        "alpha3": "DNK",
        "name": "Denmark",
        "flag_url": "//upload.wikimedia.org/wikipedia/commons/9/9c/Flag_of_Denmark.svg",
        "license": "Public domain",
        "continent": "Europe"
    },
    {
        "url": "/wiki/Djibouti",
        "alpha3": "DJI",
        "name": "Djibouti",
        "flag_url": "//upload.wikimedia.org/wikipedia/commons/3/34/Flag_of_Djibouti.svg",
        "license": "Public domain",
        "continent": "Africa"
    },
    {
        "url": "/wiki/Dominica",
        "alpha3": "DMA",
        "name": "Dominica",
        "flag_url": "//upload.wikimedia.org/wikipedia/commons/c/c4/Flag_of_Dominica.svg",
        "license": "Public domain",
        "continent": "North America"
    },
    {
        "url": "/wiki/Dominican_Republic",
        "alpha3": "DOM",
        "name": "Dominican Republic",
        "flag_url": "//upload.wikimedia.org/wikipedia/commons/9/9f/Flag_of_the_Dominican_Republic.svg",
        "license": "Public domain",
        "continent": "North America"
    },
    {
        "url": "/wiki/Ecuador",
        "alpha3": "ECU",
        "name": "Ecuador",
        "flag_url": "//upload.wikimedia.org/wikipedia/commons/e/e8/Flag_of_Ecuador.svg",
        "license": "Public domain",
        "continent": "South America"
    },
    {
        "url": "/wiki/Egypt",
        "alpha3": "EGY",
        "name": "Egypt",
        "flag_url": "//upload.wikimedia.org/wikipedia/commons/f/fe/Flag_of_Egypt.svg",
        "license": "Public domain",
        "continent": "Africa"
    },
    {
        "url": "/wiki/El_Salvador",
        "alpha3": "SLV",
        "name": "El Salvador",
        "flag_url": "//upload.wikimedia.org/wikipedia/commons/3/34/Flag_of_El_Salvador.svg",
        "license": "Public domain",
        "continent": "North America"
    },
    {
        "url": "/wiki/Equatorial_Guinea",
        "alpha3": "GNQ",
        "name": "Equatorial Guinea",
        "flag_url": "//upload.wikimedia.org/wikipedia/commons/3/31/Flag_of_Equatorial_Guinea.svg",
        "license": "Public domain",
        "continent": "Africa"
    },
    {
        "url": "/wiki/Eritrea",
        "alpha3": "ERI",
        "name": "Eritrea",
        "flag_url": "//upload.wikimedia.org/wikipedia/commons/2/29/Flag_of_Eritrea.svg",
        "license": "Public domain",
        "continent": "Africa"
    },
    {
        "url": "/wiki/Estonia",
        "alpha3": "EST",
        "name": "Estonia",
        "flag_url": "//upload.wikimedia.org/wikipedia/commons/8/8f/Flag_of_Estonia.svg",
        "license": "Public domain",
        "continent": "Europe"
    },
    {
        "url": "/wiki/Eswatini",
        "alpha3": "SWZ",
        "name": "Eswatini",
        "flag_url": "//upload.wikimedia.org/wikipedia/commons/f/fb/Flag_of_Eswatini.svg",
        "license": "Public domain",
        "continent": "Africa"
    },
    {
        "url": "/wiki/Ethiopia",
        "alpha3": "ETH",
        "name": "Ethiopia",
        "flag_url": "//upload.wikimedia.org/wikipedia/commons/7/71/Flag_of_Ethiopia.svg",
        "license": "Public domain",
        "continent": "Africa"
    },
    {
        "url": "/wiki/Falkland_Islands",
        "alpha3": "FLK",
        "name": "Falkland Islands (Malvinas)",
        "flag_url": "//upload.wikimedia.org/wikipedia/commons/8/83/Flag_of_the_Falkland_Islands.svg",
        "license": "Public domain",
        "continent": "South America"
    },
    {
        "url": "/wiki/Faroe_Islands",
        "alpha3": "FRO",
        "name": "Faroe Islands",
        "flag_url": "//upload.wikimedia.org/wikipedia/commons/3/3c/Flag_of_the_Faroe_Islands.svg",
        "license": "Public domain",
        "continent": "Europe"
    },
    {
        "url": "/wiki/Fiji",
        "alpha3": "FJI",
        "name": "Fiji",
        "flag_url": "//upload.wikimedia.org/wikipedia/commons/b/ba/Flag_of_Fiji.svg",
        "license": "Public domain",
        "continent": "Oceania"
    },
    {
        "url": "/wiki/Finland",
        "alpha3": "FIN",
        "name": "Finland",
        "flag_url": "//upload.wikimedia.org/wikipedia/commons/b/bc/Flag_of_Finland.svg",
        "license": "Public domain",
        "continent": "Europe"
    },
    {
        "url": "/wiki/France",
        "alpha3": "FRA",
        "name": "France",
        "flag_url": "//upload.wikimedia.org/wikipedia/en/c/c3/Flag_of_France.svg",
        "license": "Public domain",
        "continent": "Europe"
    },
    {
        "url": "/wiki/French_Polynesia",
        "alpha3": "PYF",
        "name": "French Polynesia",
        "flag_url": "//upload.wikimedia.org/wikipedia/commons/d/db/Flag_of_French_Polynesia.svg",
        "license": "Public domain",
        "continent": "Oceania"
    },
    {
        "url": "/wiki/Gabon",
        "alpha3": "GAB",
        "name": "Gabon",
        "flag_url": "//upload.wikimedia.org/wikipedia/commons/0/04/Flag_of_Gabon.svg",
        "license": "Public domain",
        "continent": "Africa"
    },
    {
        "url": "/wiki/Gambia",
        "alpha3": "GMB",
        "name": "Gambia",
        "flag_url": "//upload.wikimedia.org/wikipedia/commons/7/77/Flag_of_The_Gambia.svg",
        "license": "Public domain",
        "continent": "Africa"
    },
    {
        "url": "/wiki/Georgia_(country)",
        "alpha3": "GEO",
        "name": "Georgia",
        "flag_url": "//upload.wikimedia.org/wikipedia/commons/0/0f/Flag_of_Georgia.svg",
        "license": "Public domain",
        "continent": "Europe"
    },
    {
        "url": "/wiki/Germany",
        "alpha3": "DEU",
        "name": "Germany",
        "flag_url": "//upload.wikimedia.org/wikipedia/en/b/ba/Flag_of_Germany.svg",
        "license": "Public domain",
        "continent": "Europe"
    },
    {
        "url": "/wiki/Ghana",
        "alpha3": "GHA",
        "name": "Ghana",
        "flag_url": "//upload.wikimedia.org/wikipedia/commons/1/19/Flag_of_Ghana.svg",
        "license": "Public domain",
        "continent": "Africa"
    },
    {
        "url": "/wiki/Gibraltar",
        "alpha3": "GIB",
        "name": "Gibraltar",
        "flag_url": "//upload.wikimedia.org/wikipedia/commons/0/02/Flag_of_Gibraltar.svg",
        "license": "Public domain",
        "continent": "Europe"
    },
    {
        "url": "/wiki/Greece",
        "alpha3": "GRC",
        "name": "Greece",
        "flag_url": "//upload.wikimedia.org/wikipedia/commons/5/5c/Flag_of_Greece.svg",
        "license": "Public domain",
        "continent": "Europe"
    },
    {
        "url": "/wiki/Grenada",
        "alpha3": "GRD",
        "name": "Grenada",
        "flag_url": "//upload.wikimedia.org/wikipedia/commons/b/bc/Flag_of_Grenada.svg",
        "license": "Public domain",
        "continent": "North America"
    },
    {
        "url": "/wiki/Guam",
        "alpha3": "GUM",
        "name": "Guam",
        "flag_url": "//upload.wikimedia.org/wikipedia/commons/0/07/Flag_of_Guam.svg",
        "license": "Public domain",
        "continent": "Oceania"
    },
    {
        "url": "/wiki/Guatemala",
        "alpha3": "GTM",
        "name": "Guatemala",
        "flag_url": "//upload.wikimedia.org/wikipedia/commons/e/ec/Flag_of_Guatemala.svg",
        "license": "Public domain",
        "continent": "North America"
    },
    {
        "url": "/wiki/Bailiwick_of_Guernsey",
        "alpha3": "GGY",
        "name": "Guernsey",
        "flag_url": "//upload.wikimedia.org/wikipedia/commons/f/fa/Flag_of_Guernsey.svg",
        "license": "Public domain",
        "continent": "Europe"
    },
    {
        "url": "/wiki/Guinea",
        "alpha3": "GIN",
        "name": "Guinea",
        "flag_url": "//upload.wikimedia.org/wikipedia/commons/e/ed/Flag_of_Guinea.svg",
        "license": "Public domain",
        "continent": "Africa"
    },
    {
        "url": "/wiki/Guinea-Bissau",
        "alpha3": "GNB",
        "name": "Guinea-Bissau",
        "flag_url": "//upload.wikimedia.org/wikipedia/commons/0/01/Flag_of_Guinea-Bissau.svg",
        "license": "Public domain",
        "continent": "Africa"
    },
    {
        "url": "/wiki/Guyana",
        "alpha3": "GUY",
        "name": "Guyana",
        "flag_url": "//upload.wikimedia.org/wikipedia/commons/9/99/Flag_of_Guyana.svg",
        "license": "Public domain",
        "continent": "South America"
    },
    {
        "url": "/wiki/Haiti",
        "alpha3": "HTI",
        "name": "Haiti",
        "flag_url": "//upload.wikimedia.org/wikipedia/commons/5/56/Flag_of_Haiti.svg",
        "license": "Public domain",
        "continent": "North America"
    },
    {
        "url": "/wiki/Vatican_City",
        "alpha3": "VAT",
        "name": "Holy See",
        "flag_url": "//upload.wikimedia.org/wikipedia/commons/0/00/Flag_of_the_Vatican_City.svg",
        "license": "Public domain",
        "continent": "Europe"
    },
    {
        "url": "/wiki/Honduras",
        "alpha3": "HND",
        "name": "Honduras",
        "flag_url": "//upload.wikimedia.org/wikipedia/commons/8/82/Flag_of_Honduras.svg",
        "license": "Public domain",
        "continent": "North America"
    },
    {
        "url": "/wiki/Hong_Kong",
        "alpha3": "HKG",
        "name": "Hong Kong",
        "flag_url": "//upload.wikimedia.org/wikipedia/commons/5/5b/Flag_of_Hong_Kong.svg",
        "license": "Public domain",
        "continent": "Asia"
    },
    {
        "url": "/wiki/Hungary",
        "alpha3": "HUN",
        "name": "Hungary",
        "flag_url": "//upload.wikimedia.org/wikipedia/commons/c/c1/Flag_of_Hungary.svg",
        "license": "Public domain",
        "continent": "Europe"
    },
    {
        "url": "/wiki/Iceland",
        "alpha3": "ISL",
        "name": "Iceland",
        "flag_url": "//upload.wikimedia.org/wikipedia/commons/c/ce/Flag_of_Iceland.svg",
        "license": "Public domain",
        "continent": "Europe"
    },
    {
        "url": "/wiki/India",
        "alpha3": "IND",
        "name": "India",
        "flag_url": "//upload.wikimedia.org/wikipedia/en/4/41/Flag_of_India.svg",
        "license": "Public domain",
        "continent": "Asia"
    },
    {
        "url": "/wiki/Indonesia",
        "alpha3": "IDN",
        "name": "Indonesia",
        "flag_url": "//upload.wikimedia.org/wikipedia/commons/9/9f/Flag_of_Indonesia.svg",
        "license": "Public domain",
        "continent": "Asia"
    },
    {
        "url": "/wiki/Iran",
        "alpha3": "IRN",
        "name": "Iran (Islamic Republic of)",
        "flag_url": "//upload.wikimedia.org/wikipedia/commons/c/ca/Flag_of_Iran.svg",
        "license": "Public domain",
        "continent": "Asia"
    },
    {
        "url": "/wiki/Iraq",
        "alpha3": "IRQ",
        "name": "Iraq",
        "flag_url": "//upload.wikimedia.org/wikipedia/commons/f/f6/Flag_of_Iraq.svg",
        "license": "Public domain",
        "continent": "Asia"
    },
    {
        "url": "/wiki/Republic_of_Ireland",
        "alpha3": "IRL",
        "name": "Ireland",
        "flag_url": "//upload.wikimedia.org/wikipedia/commons/4/45/Flag_of_Ireland.svg",
        "license": "Public domain",
        "continent": "Europe"
    },
    {
        "url": "/wiki/Isle_of_Man",
        "alpha3": "IMN",
        "name": "Isle of Man",
        "flag_url": "//upload.wikimedia.org/wikipedia/commons/b/bc/Flag_of_the_Isle_of_Man.svg",
        "license": "Public domain",
        "continent": "Europe"
    },
    {
        "url": "/wiki/Israel",
        "alpha3": "ISR",
        "name": "Israel",
        "flag_url": "//upload.wikimedia.org/wikipedia/commons/d/d4/Flag_of_Israel.svg",
        "license": "Public domain",
        "continent": "Asia"
    },
    {
        "url": "/wiki/Italy",
        "alpha3": "ITA",
        "name": "Italy",
        "flag_url": "//upload.wikimedia.org/wikipedia/en/0/03/Flag_of_Italy.svg",
        "license": "Public domain",
        "continent": "Europe"
    },
    {
        "url": "/wiki/Jamaica",
        "alpha3": "JAM",
        "name": "Jamaica",
        "flag_url": "//upload.wikimedia.org/wikipedia/commons/0/0a/Flag_of_Jamaica.svg",
        "license": "Public domain",
        "continent": "North America"
    },
    {
        "url": "/wiki/Japan",
        "alpha3": "JPN",
        "name": "Japan",
        "flag_url": "//upload.wikimedia.org/wikipedia/en/9/9e/Flag_of_Japan.svg",
        "license": "Public domain",
        "continent": "Asia"
    },
    {
        "url": "/wiki/Jersey",
        "alpha3": "JEY",
        "name": "Jersey",
        "flag_url": "//upload.wikimedia.org/wikipedia/commons/1/1c/Flag_of_Jersey.svg",
        "license": "Public domain",
        "continent": "Europe"
    },
    {
        "url": "/wiki/Jordan",
        "alpha3": "JOR",
        "name": "Jordan",
        "flag_url": "//upload.wikimedia.org/wikipedia/commons/c/c0/Flag_of_Jordan.svg",
        "license": "Public domain",
        "continent": "Asia"
    },
    {
        "url": "/wiki/Kazakhstan",
        "alpha3": "KAZ",
        "name": "Kazakhstan",
        "flag_url": "//upload.wikimedia.org/wikipedia/commons/d/d3/Flag_of_Kazakhstan.svg",
        "license": "Public domain",
        "continent": "Asia"
    },
    {
        "url": "/wiki/Kenya",
        "alpha3": "KEN",
        "name": "Kenya",
        "flag_url": "//upload.wikimedia.org/wikipedia/commons/4/49/Flag_of_Kenya.svg",
        "license": "Public domain",
        "continent": "Africa"
    },
    {
        "url": "/wiki/Kiribati",
        "alpha3": "KIR",
        "name": "Kiribati",
        "flag_url": "//upload.wikimedia.org/wikipedia/commons/d/d3/Flag_of_Kiribati.svg",
        "license": "Public domain",
        "continent": "Oceania"
    },
    {
        "url": "/wiki/North_Korea",
        "alpha3": "PRK",
        "name": "Korea (Democratic People's Republic of)",
        "flag_url": "//upload.wikimedia.org/wikipedia/commons/5/51/Flag_of_North_Korea.svg",
        "license": "Public domain",
        "continent": "Asia"
    },
    {
        "url": "/wiki/South_Korea",
        "alpha3": "KOR",
        "name": "Korea - Republic of",
        "flag_url": "//upload.wikimedia.org/wikipedia/commons/0/09/Flag_of_South_Korea.svg",
        "license": "Public domain",
        "continent": "Asia"
    },
    {
        "url": "/wiki/Kuwait",
        "alpha3": "KWT",
        "name": "Kuwait",
        "flag_url": "//upload.wikimedia.org/wikipedia/commons/a/aa/Flag_of_Kuwait.svg",
        "license": "Public domain",
        "continent": "Asia"
    },
    {
        "url": "/wiki/Kyrgyzstan",
        "alpha3": "KGZ",
        "name": "Kyrgyzstan",
        "flag_url": "//upload.wikimedia.org/wikipedia/commons/c/c7/Flag_of_Kyrgyzstan.svg",
        "license": "Public domain",
        "continent": "Asia"
    },
    {
        "url": "/wiki/Laos",
        "alpha3": "LAO",
        "name": "Lao People's Democratic Republic",
        "flag_url": "//upload.wikimedia.org/wikipedia/commons/5/56/Flag_of_Laos.svg",
        "license": "Public domain",
        "continent": "Asia"
    },
    {
        "url": "/wiki/Latvia",
        "alpha3": "LVA",
        "name": "Latvia",
        "flag_url": "//upload.wikimedia.org/wikipedia/commons/8/84/Flag_of_Latvia.svg",
        "license": "Public domain",
        "continent": "Europe"
    },
    {
        "url": "/wiki/Lebanon",
        "alpha3": "LBN",
        "name": "Lebanon",
        "flag_url": "//upload.wikimedia.org/wikipedia/commons/5/59/Flag_of_Lebanon.svg",
        "license": "Public domain",
        "continent": "Asia"
    },
    {
        "url": "/wiki/Lesotho",
        "alpha3": "LSO",
        "name": "Lesotho",
        "flag_url": "//upload.wikimedia.org/wikipedia/commons/4/4a/Flag_of_Lesotho.svg",
        "license": "Public domain",
        "continent": "Africa"
    },
    {
        "url": "/wiki/Liberia",
        "alpha3": "LBR",
        "name": "Liberia",
        "flag_url": "//upload.wikimedia.org/wikipedia/commons/b/b8/Flag_of_Liberia.svg",
        "license": "Public domain",
        "continent": "Africa"
    },
    {
        "url": "/wiki/Libya",
        "alpha3": "LBY",
        "name": "Libya",
        "flag_url": "//upload.wikimedia.org/wikipedia/commons/0/05/Flag_of_Libya.svg",
        "license": "Public domain",
        "continent": "Africa"
    },
    {
        "url": "/wiki/Liechtenstein",
        "alpha3": "LIE",
        "name": "Liechtenstein",
        "flag_url": "//upload.wikimedia.org/wikipedia/commons/4/47/Flag_of_Liechtenstein.svg",
        "license": "Public domain",
        "continent": "Europe"
    },
    {
        "url": "/wiki/Lithuania",
        "alpha3": "LTU",
        "name": "Lithuania",
        "flag_url": "//upload.wikimedia.org/wikipedia/commons/1/11/Flag_of_Lithuania.svg",
        "license": "Public domain",
        "continent": "Europe"
    },
    {
        "url": "/wiki/Luxembourg",
        "alpha3": "LUX",
        "name": "Luxembourg",
        "flag_url": "//upload.wikimedia.org/wikipedia/commons/d/da/Flag_of_Luxembourg.svg",
        "license": "Public domain",
        "continent": "Europe"
    },
    {
        "url": "/wiki/Macau",
        "alpha3": "MAC",
        "name": "Macao",
        "flag_url": "//upload.wikimedia.org/wikipedia/commons/6/63/Flag_of_Macau.svg",
        "license": "Public domain",
        "continent": "Asia"
    },
    {
        "url": "/wiki/Madagascar",
        "alpha3": "MDG",
        "name": "Madagascar",
        "flag_url": "//upload.wikimedia.org/wikipedia/commons/b/bc/Flag_of_Madagascar.svg",
        "license": "Public domain",
        "continent": "Africa"
    },
    {
        "url": "/wiki/Malawi",
        "alpha3": "MWI",
        "name": "Malawi",
        "flag_url": "//upload.wikimedia.org/wikipedia/commons/d/d1/Flag_of_Malawi.svg",
        "license": "Public domain",
        "continent": "Africa"
    },
    {
        "url": "/wiki/Malaysia",
        "alpha3": "MYS",
        "name": "Malaysia",
        "flag_url": "//upload.wikimedia.org/wikipedia/commons/6/66/Flag_of_Malaysia.svg",
        "license": "Public domain",
        "continent": "Asia"
    },
    {
        "url": "/wiki/Maldives",
        "alpha3": "MDV",
        "name": "Maldives",
        "flag_url": "//upload.wikimedia.org/wikipedia/commons/0/0f/Flag_of_Maldives.svg",
        "license": "Public domain",
        "continent": "Asia"
    },
    {
        "url": "/wiki/Mali",
        "alpha3": "MLI",
        "name": "Mali",
        "flag_url": "//upload.wikimedia.org/wikipedia/commons/9/92/Flag_of_Mali.svg",
        "license": "Public domain",
        "continent": "Africa"
    },
    {
        "url": "/wiki/Malta",
        "alpha3": "MLT",
        "name": "Malta",
        "flag_url": "//upload.wikimedia.org/wikipedia/commons/7/73/Flag_of_Malta.svg",
        "license": "Public domain",
        "continent": "Europe"
    },
    {
        "url": "/wiki/Marshall_Islands",
        "alpha3": "MHL",
        "name": "Marshall Islands",
        "flag_url": "//upload.wikimedia.org/wikipedia/commons/2/2e/Flag_of_the_Marshall_Islands.svg",
        "license": "Public domain",
        "continent": "Oceania"
    },
    {
        "url": "/wiki/Mauritania",
        "alpha3": "MRT",
        "name": "Mauritania",
        "flag_url": "//upload.wikimedia.org/wikipedia/commons/4/43/Flag_of_Mauritania.svg",
        "license": "Public domain",
        "continent": "Africa"
    },
    {
        "url": "/wiki/Mauritius",
        "alpha3": "MUS",
        "name": "Mauritius",
        "flag_url": "//upload.wikimedia.org/wikipedia/commons/7/77/Flag_of_Mauritius.svg",
        "license": "Public domain",
        "continent": "Africa"
    },
    {
        "url": "/wiki/Mexico",
        "alpha3": "MEX",
        "name": "Mexico",
        "flag_url": "//upload.wikimedia.org/wikipedia/commons/f/fc/Flag_of_Mexico.svg",
        "license": "Public domain",
        "continent": "North America"
    },
    {
        "url": "/wiki/Federated_States_of_Micronesia",
        "alpha3": "FSM",
        "name": "Micronesia (Federated States of)",
        "flag_url": "//upload.wikimedia.org/wikipedia/commons/e/e4/Flag_of_the_Federated_States_of_Micronesia.svg",
        "license": "Public domain",
        "continent": "Oceania"
    },
    {
        "url": "/wiki/Moldova",
        "alpha3": "MDA",
        "name": "Moldova - Republic of",
        "flag_url": "//upload.wikimedia.org/wikipedia/commons/2/27/Flag_of_Moldova.svg",
        "license": "Public domain",
        "continent": "Europe"
    },
    {
        "url": "/wiki/Monaco",
        "alpha3": "MCO",
        "name": "Monaco",
        "flag_url": "//upload.wikimedia.org/wikipedia/commons/e/ea/Flag_of_Monaco.svg",
        "license": "Public domain",
        "continent": "Europe"
    },
    {
        "url": "/wiki/Mongolia",
        "alpha3": "MNG",
        "name": "Mongolia",
        "flag_url": "//upload.wikimedia.org/wikipedia/commons/4/4c/Flag_of_Mongolia.svg",
        "license": "Public domain",
        "continent": "Asia"
    },
    {
        "url": "/wiki/Montenegro",
        "alpha3": "MNE",
        "name": "Montenegro",
        "flag_url": "//upload.wikimedia.org/wikipedia/commons/6/64/Flag_of_Montenegro.svg",
        "license": "Public domain",
        "continent": "Europe"
    },
    {
        "url": "/wiki/Montserrat",
        "alpha3": "MSR",
        "name": "Montserrat",
        "flag_url": "//upload.wikimedia.org/wikipedia/commons/d/d0/Flag_of_Montserrat.svg",
        "license": "Public domain",
        "continent": "North America"
    },
    {
        "url": "/wiki/Morocco",
        "alpha3": "MAR",
        "name": "Morocco",
        "flag_url": "//upload.wikimedia.org/wikipedia/commons/2/2c/Flag_of_Morocco.svg",
        "license": "Public domain",
        "continent": "Africa"
    },
    {
        "url": "/wiki/Mozambique",
        "alpha3": "MOZ",
        "name": "Mozambique",
        "flag_url": "//upload.wikimedia.org/wikipedia/commons/d/d0/Flag_of_Mozambique.svg",
        "license": "Public domain",
        "continent": "Africa"
    },
    {
        "url": "/wiki/Myanmar",
        "alpha3": "MMR",
        "name": "Myanmar",
        "flag_url": "//upload.wikimedia.org/wikipedia/commons/8/8c/Flag_of_Myanmar.svg",
        "license": "Public domain",
        "continent": "Asia"
    },
    {
        "url": "/wiki/Namibia",
        "alpha3": "NAM",
        "name": "Namibia",
        "flag_url": "//upload.wikimedia.org/wikipedia/commons/0/00/Flag_of_Namibia.svg",
        "license": "Public domain",
        "continent": "Africa"
    },
    {
        "url": "/wiki/Nauru",
        "alpha3": "NRU",
        "name": "Nauru",
        "flag_url": "//upload.wikimedia.org/wikipedia/commons/3/30/Flag_of_Nauru.svg",
        "license": "Public domain",
        "continent": "Oceania"
    },
    {
        "url": "/wiki/Nepal",
        "alpha3": "NPL",
        "name": "Nepal",
        "flag_url": "//upload.wikimedia.org/wikipedia/commons/9/9b/Flag_of_Nepal.svg",
        "license": "Public domain",
        "continent": "Asia"
    },
    {
        "url": "/wiki/Kingdom_of_the_Netherlands",
        "alpha3": "NLD",
        "name": "Netherlands",
        "flag_url": "//upload.wikimedia.org/wikipedia/commons/2/20/Flag_of_the_Netherlands.svg",
        "license": "Public domain",
        "continent": "Europe"
    },
    {
        "url": "/wiki/New_Caledonia",
        "alpha3": "NCL",
        "name": "New Caledonia",
        "flag_url": "//upload.wikimedia.org/wikipedia/commons/0/0c/Drapeau_de_Nouvelle-Cal%C3%A9donie.png",
        "license": "Creative Commons Attribution-Share Alike 4.0 International",
        "continent": "Oceania"
    },
    {
        "url": "/wiki/New_Zealand",
        "alpha3": "NZL",
        "name": "New Zealand",
        "flag_url": "//upload.wikimedia.org/wikipedia/commons/3/3e/Flag_of_New_Zealand.svg",
        "license": "Public domain",
        "continent": "Oceania"
    },
    {
        "url": "/wiki/Nicaragua",
        "alpha3": "NIC",
        "name": "Nicaragua",
        "flag_url": "//upload.wikimedia.org/wikipedia/commons/1/19/Flag_of_Nicaragua.svg",
        "license": "Public domain",
        "continent": "North America"
    },
    {
        "url": "/wiki/Niger",
        "alpha3": "NER",
        "name": "Niger",
        "flag_url": "//upload.wikimedia.org/wikipedia/commons/f/f4/Flag_of_Niger.svg",
        "license": "Public domain",
        "continent": "Africa"
    },
    {
        "url": "/wiki/Nigeria",
        "alpha3": "NGA",
        "name": "Nigeria",
        "flag_url": "//upload.wikimedia.org/wikipedia/commons/7/79/Flag_of_Nigeria.svg",
        "license": "Public domain",
        "continent": "Africa"
    },
    {
        "url": "/wiki/Niue",
        "alpha3": "NIU",
        "name": "Niue",
        "flag_url": "//upload.wikimedia.org/wikipedia/commons/0/01/Flag_of_Niue.svg",
        "license": "Public domain",
        "continent": "Oceania"
    },
    {
        "url": "/wiki/Norfolk_Island",
        "alpha3": "NFK",
        "name": "Norfolk Island",
        "flag_url": "//upload.wikimedia.org/wikipedia/commons/4/48/Flag_of_Norfolk_Island.svg",
        "license": "Public domain",
        "continent": "Oceania"
    },
    {
        "url": "/wiki/North_Macedonia",
        "alpha3": "MKD",
        "name": "North Macedonia",
        "flag_url": "//upload.wikimedia.org/wikipedia/commons/7/79/Flag_of_North_Macedonia.svg",
        "license": "Public domain",
        "continent": "Europe"
    },
    {
        "url": "/wiki/Northern_Mariana_Islands",
        "alpha3": "MNP",
        "name": "Northern Mariana Islands",
        "flag_url": "//upload.wikimedia.org/wikipedia/commons/e/e0/Flag_of_the_Northern_Mariana_Islands.svg",
        "license": "Public domain",
        "continent": "Oceania"
    },
    {
        "url": "/wiki/Norway",
        "alpha3": "NOR",
        "name": "Norway",
        "flag_url": "//upload.wikimedia.org/wikipedia/commons/d/d9/Flag_of_Norway.svg",
        "license": "Public domain",
        "continent": "Europe"
    },
    {
        "url": "/wiki/Oman",
        "alpha3": "OMN",
        "name": "Oman",
        "flag_url": "//upload.wikimedia.org/wikipedia/commons/d/dd/Flag_of_Oman.svg",
        "license": "Public domain",
        "continent": "Asia"
    },
    {
        "url": "/wiki/Pakistan",
        "alpha3": "PAK",
        "name": "Pakistan",
        "flag_url": "//upload.wikimedia.org/wikipedia/commons/3/32/Flag_of_Pakistan.svg",
        "license": "Public domain",
        "continent": "Asia"
    },
    {
        "url": "/wiki/Palau",
        "alpha3": "PLW",
        "name": "Palau",
        "flag_url": "//upload.wikimedia.org/wikipedia/commons/4/48/Flag_of_Palau.svg",
        "license": "Public domain",
        "continent": "Oceania"
    },
    {
        "url": "/wiki/State_of_Palestine",
        "alpha3": "PSE",
        "name": "Palestine - State of",
        "flag_url": "//upload.wikimedia.org/wikipedia/commons/0/00/Flag_of_Palestine.svg",
        "license": "Public domain",
        "continent": "Asia"
    },
    {
        "url": "/wiki/Panama",
        "alpha3": "PAN",
        "name": "Panama",
        "flag_url": "//upload.wikimedia.org/wikipedia/commons/a/ab/Flag_of_Panama.svg",
        "license": "Public domain",
        "continent": "North America"
    },
    {
        "url": "/wiki/Papua_New_Guinea",
        "alpha3": "PNG",
        "name": "Papua New Guinea",
        "flag_url": "//upload.wikimedia.org/wikipedia/commons/e/e3/Flag_of_Papua_New_Guinea.svg",
        "license": "Public domain",
        "continent": "Oceania"
    },
    {
        "url": "/wiki/Paraguay",
        "alpha3": "PRY",
        "name": "Paraguay",
        "flag_url": "//upload.wikimedia.org/wikipedia/commons/2/27/Flag_of_Paraguay.svg",
        "license": "Public domain",
        "continent": "South America"
    },
    {
        "url": "/wiki/Peru",
        "alpha3": "PER",
        "name": "Peru",
        "flag_url": "//upload.wikimedia.org/wikipedia/commons/c/cf/Flag_of_Peru.svg",
        "license": "Public domain",
        "continent": "South America"
    },
    {
        "url": "/wiki/Philippines",
        "alpha3": "PHL",
        "name": "Philippines",
        "flag_url": "//upload.wikimedia.org/wikipedia/commons/9/99/Flag_of_the_Philippines.svg",
        "license": "Public domain",
        "continent": "Asia"
    },
    {
        "url": "/wiki/Pitcairn_Islands",
        "alpha3": "PCN",
        "name": "Pitcairn",
        "flag_url": "//upload.wikimedia.org/wikipedia/commons/8/88/Flag_of_the_Pitcairn_Islands.svg",
        "license": "Public domain",
        "continent": "Oceania"
    },
    {
        "url": "/wiki/Poland",
        "alpha3": "POL",
        "name": "Poland",
        "flag_url": "//upload.wikimedia.org/wikipedia/en/1/12/Flag_of_Poland.svg",
        "license": "Public domain",
        "continent": "Europe"
    },
    {
        "url": "/wiki/Portugal",
        "alpha3": "PRT",
        "name": "Portugal",
        "flag_url": "//upload.wikimedia.org/wikipedia/commons/5/5c/Flag_of_Portugal.svg",
        "license": "Public domain",
        "continent": "Europe"
    },
    {
        "url": "/wiki/Puerto_Rico",
        "alpha3": "PRI",
        "name": "Puerto Rico",
        "flag_url": "//upload.wikimedia.org/wikipedia/commons/2/28/Flag_of_Puerto_Rico.svg",
        "license": "Public domain",
        "continent": "North America"
    },
    {
        "url": "/wiki/Qatar",
        "alpha3": "QAT",
        "name": "Qatar",
        "flag_url": "//upload.wikimedia.org/wikipedia/commons/6/65/Flag_of_Qatar.svg",
        "license": "Public domain",
        "continent": "Asia"
    },
    {
        "url": "/wiki/Romania",
        "alpha3": "ROU",
        "name": "Romania",
        "flag_url": "//upload.wikimedia.org/wikipedia/commons/7/73/Flag_of_Romania.svg",
        "license": "Public domain",
        "continent": "Europe"
    },
    {
        "url": "/wiki/Russia",
        "alpha3": "RUS",
        "name": "Russian Federation",
        "flag_url": "//upload.wikimedia.org/wikipedia/en/f/f3/Flag_of_Russia.svg",
        "license": "Public domain",
        "continent": "Europe"
    },
    {
        "url": "/wiki/Rwanda",
        "alpha3": "RWA",
        "name": "Rwanda",
        "flag_url": "//upload.wikimedia.org/wikipedia/commons/1/17/Flag_of_Rwanda.svg",
        "license": "Public domain",
        "continent": "Africa"
    },
    {
        "url": "/wiki/Saint_Barth%C3%A9lemy",
        "alpha3": "BLM",
        "name": "Saint Barth\u00e9lemy",
        "flag_url": "//upload.wikimedia.org/wikipedia/en/c/c3/Flag_of_France.svg",
        "license": "Public domain",
        "continent": "North America"
    },
    {
        "url": "/wiki/Saint_Helena,_Ascension_and_Tristan_da_Cunha",
        "alpha3": "SHN",
        "name": "Saint Helena - Ascension and Tristan da Cunha",
        "flag_url": "//upload.wikimedia.org/wikipedia/en/a/ae/Flag_of_the_United_Kingdom.svg",
        "license": "Public domain",
        "continent": "Africa"
    },
    {
        "url": "/wiki/Saint_Kitts_and_Nevis",
        "alpha3": "KNA",
        "name": "Saint Kitts and Nevis",
        "flag_url": "//upload.wikimedia.org/wikipedia/commons/f/fe/Flag_of_Saint_Kitts_and_Nevis.svg",
        "license": "Public domain",
        "continent": "North America"
    },
    {
        "url": "/wiki/Saint_Lucia",
        "alpha3": "LCA",
        "name": "Saint Lucia",
        "flag_url": "//upload.wikimedia.org/wikipedia/commons/9/9f/Flag_of_Saint_Lucia.svg",
        "license": "Public domain",
        "continent": "North America"
    },
    {
        "url": "/wiki/Collectivity_of_Saint_Martin",
        "alpha3": "MAF",
        "name": "Saint Martin (French part)",
        "flag_url": "//upload.wikimedia.org/wikipedia/en/c/c3/Flag_of_France.svg",
        "license": "Public domain",
        "continent": "North America"
    },
    {
        "url": "/wiki/Saint_Vincent_and_the_Grenadines",
        "alpha3": "VCT",
        "name": "Saint Vincent and the Grenadines",
        "flag_url": "//upload.wikimedia.org/wikipedia/commons/6/6d/Flag_of_Saint_Vincent_and_the_Grenadines.svg",
        "license": "Public domain",
        "continent": "North America"
    },
    {
        "url": "/wiki/Samoa",
        "alpha3": "WSM",
        "name": "Samoa",
        "flag_url": "//upload.wikimedia.org/wikipedia/commons/3/31/Flag_of_Samoa.svg",
        "license": "Public domain",
        "continent": "Oceania"
    },
    {
        "url": "/wiki/San_Marino",
        "alpha3": "SMR",
        "name": "San Marino",
        "flag_url": "//upload.wikimedia.org/wikipedia/commons/b/b1/Flag_of_San_Marino.svg",
        "license": "Public domain",
        "continent": "Europe"
    },
    {
        "url": "/wiki/S%C3%A3o_Tom%C3%A9_and_Pr%C3%ADncipe",
        "alpha3": "STP",
        "name": "Sao Tome and Principe",
        "flag_url": "//upload.wikimedia.org/wikipedia/commons/4/4f/Flag_of_Sao_Tome_and_Principe.svg",
        "license": "Public domain",
        "continent": "Africa"
    },
    {
        "url": "/wiki/Senegal",
        "alpha3": "SEN",
        "name": "Senegal",
        "flag_url": "//upload.wikimedia.org/wikipedia/commons/f/fd/Flag_of_Senegal.svg",
        "license": "Public domain",
        "continent": "Africa"
    },
    {
        "url": "/wiki/Serbia",
        "alpha3": "SRB",
        "name": "Serbia",
        "flag_url": "//upload.wikimedia.org/wikipedia/commons/f/ff/Flag_of_Serbia.svg",
        "license": "Public domain",
        "continent": "Europe"
    },
    {
        "url": "/wiki/Seychelles",
        "alpha3": "SYC",
        "name": "Seychelles",
        "flag_url": "//upload.wikimedia.org/wikipedia/commons/f/fc/Flag_of_Seychelles.svg",
        "license": "Public domain",
        "continent": "Africa"
    },
    {
        "url": "/wiki/Sierra_Leone",
        "alpha3": "SLE",
        "name": "Sierra Leone",
        "flag_url": "//upload.wikimedia.org/wikipedia/commons/1/17/Flag_of_Sierra_Leone.svg",
        "license": "Public domain",
        "continent": "Africa"
    },
    {
        "url": "/wiki/Singapore",
        "alpha3": "SGP",
        "name": "Singapore",
        "flag_url": "//upload.wikimedia.org/wikipedia/commons/4/48/Flag_of_Singapore.svg",
        "license": "Public domain",
        "continent": "Asia"
    },
    {
        "url": "/wiki/Sint_Maarten",
        "alpha3": "SXM",
        "name": "Sint Maarten (Dutch part)",
        "flag_url": "//upload.wikimedia.org/wikipedia/commons/d/d3/Flag_of_Sint_Maarten.svg",
        "license": "Public domain",
        "continent": "North America"
    },
    {
        "url": "/wiki/Slovakia",
        "alpha3": "SVK",
        "name": "Slovakia",
        "flag_url": "//upload.wikimedia.org/wikipedia/commons/e/e6/Flag_of_Slovakia.svg",
        "license": "Public domain",
        "continent": "Europe"
    },
    {
        "url": "/wiki/Slovenia",
        "alpha3": "SVN",
        "name": "Slovenia",
        "flag_url": "//upload.wikimedia.org/wikipedia/commons/f/f0/Flag_of_Slovenia.svg",
        "license": "Public domain",
        "continent": "Europe"
    },
    {
        "url": "/wiki/Solomon_Islands",
        "alpha3": "SLB",
        "name": "Solomon Islands",
        "flag_url": "//upload.wikimedia.org/wikipedia/commons/7/74/Flag_of_the_Solomon_Islands.svg",
        "license": "Public domain",
        "continent": "Oceania"
    },
    {
        "url": "/wiki/Somalia",
        "alpha3": "SOM",
        "name": "Somalia",
        "flag_url": "//upload.wikimedia.org/wikipedia/commons/a/a0/Flag_of_Somalia.svg",
        "license": "Public domain",
        "continent": "Africa"
    },
    {
        "url": "/wiki/South_Africa",
        "alpha3": "ZAF",
        "name": "South Africa",
        "flag_url": "//upload.wikimedia.org/wikipedia/commons/a/af/Flag_of_South_Africa.svg",
        "license": "Public domain",
        "continent": "Africa"
    },
    {
        "url": "/wiki/South_Sudan",
        "alpha3": "SSD",
        "name": "South Sudan",
        "flag_url": "//upload.wikimedia.org/wikipedia/commons/7/7a/Flag_of_South_Sudan.svg",
        "license": "Public domain",
        "continent": "Africa"
    },
    {
        "url": "/wiki/Spain",
        "alpha3": "ESP",
        "name": "Spain",
        "flag_url": "//upload.wikimedia.org/wikipedia/commons/8/89/Bandera_de_Espa%C3%B1a.svg",
        "license": "Public domain",
        "continent": "Europe"
    },
    {
        "url": "/wiki/Sri_Lanka",
        "alpha3": "LKA",
        "name": "Sri Lanka",
        "flag_url": "//upload.wikimedia.org/wikipedia/commons/1/11/Flag_of_Sri_Lanka.svg",
        "license": "Public domain",
        "continent": "Asia"
    },
    {
        "url": "/wiki/Sudan",
        "alpha3": "SDN",
        "name": "Sudan",
        "flag_url": "//upload.wikimedia.org/wikipedia/commons/0/01/Flag_of_Sudan.svg",
        "license": "Public domain",
        "continent": "Africa"
    },
    {
        "url": "/wiki/Suriname",
        "alpha3": "SUR",
        "name": "Suriname",
        "flag_url": "//upload.wikimedia.org/wikipedia/commons/6/60/Flag_of_Suriname.svg",
        "license": "Public domain",
        "continent": "South America"
    },
    {
        "url": "/wiki/Svalbard_and_Jan_Mayen",
        "alpha3": "SJM",
        "name": "Svalbard and Jan Mayen",
        "flag_url": "//upload.wikimedia.org/wikipedia/commons/d/d9/Flag_of_Norway.svg",
        "license": "Public domain",
        "continent": "Europe"
    },
    {
        "url": "/wiki/Sweden",
        "alpha3": "SWE",
        "name": "Sweden",
        "flag_url": "//upload.wikimedia.org/wikipedia/en/4/4c/Flag_of_Sweden.svg",
        "license": "Public domain",
        "continent": "Europe"
    },
    {
        "url": "/wiki/Switzerland",
        "alpha3": "CHE",
        "name": "Switzerland",
        "flag_url": "//upload.wikimedia.org/wikipedia/commons/f/f3/Flag_of_Switzerland.svg",
        "license": "Public domain",
        "continent": "Europe"
    },
    {
        "url": "/wiki/Syria",
        "alpha3": "SYR",
        "name": "Syrian Arab Republic",
        "flag_url": "//upload.wikimedia.org/wikipedia/commons/5/53/Flag_of_Syria.svg",
        "license": "Public domain",
        "continent": "Asia"
    },
    {
        "url": "/wiki/Tajikistan",
        "alpha3": "TJK",
        "name": "Tajikistan",
        "flag_url": "//upload.wikimedia.org/wikipedia/commons/d/d0/Flag_of_Tajikistan.svg",
        "license": "Public domain",
        "continent": "Asia"
    },
    {
        "url": "/wiki/Tanzania",
        "alpha3": "TZA",
        "name": "Tanzania - United Republic of",
        "flag_url": "//upload.wikimedia.org/wikipedia/commons/3/38/Flag_of_Tanzania.svg",
        "license": "Public domain",
        "continent": "Africa"
    },
    {
        "url": "/wiki/Thailand",
        "alpha3": "THA",
        "name": "Thailand",
        "flag_url": "//upload.wikimedia.org/wikipedia/commons/a/a9/Flag_of_Thailand.svg",
        "license": "Public domain",
        "continent": "Asia"
    },
    {
        "url": "/wiki/East_Timor",
        "alpha3": "TLS",
        "name": "Timor-Leste",
        "flag_url": "//upload.wikimedia.org/wikipedia/commons/2/26/Flag_of_East_Timor.svg",
        "license": "Public domain",
        "continent": "Asia"
    },
    {
        "url": "/wiki/Togo",
        "alpha3": "TGO",
        "name": "Togo",
        "flag_url": "//upload.wikimedia.org/wikipedia/commons/6/68/Flag_of_Togo.svg",
        "license": "Public domain",
        "continent": "Africa"
    },
    {
        "url": "/wiki/Tokelau",
        "alpha3": "TKL",
        "name": "Tokelau",
        "flag_url": "//upload.wikimedia.org/wikipedia/commons/8/8e/Flag_of_Tokelau.svg",
        "license": "Public domain",
        "continent": "Oceania"
    },
    {
        "url": "/wiki/Tonga",
        "alpha3": "TON",
        "name": "Tonga",
        "flag_url": "//upload.wikimedia.org/wikipedia/commons/9/9a/Flag_of_Tonga.svg",
        "license": "Public domain",
        "continent": "Oceania"
    },
    {
        "url": "/wiki/Trinidad_and_Tobago",
        "alpha3": "TTO",
        "name": "Trinidad and Tobago",
        "flag_url": "//upload.wikimedia.org/wikipedia/commons/6/64/Flag_of_Trinidad_and_Tobago.svg",
        "license": "Public domain",
        "continent": "North America"
    },
    {
        "url": "/wiki/Tunisia",
        "alpha3": "TUN",
        "name": "Tunisia",
        "flag_url": "//upload.wikimedia.org/wikipedia/commons/c/ce/Flag_of_Tunisia.svg",
        "license": "Public domain",
        "continent": "Africa"
    },
    {
        "url": "/wiki/Turkey",
        "alpha3": "TUR",
        "name": "T\u00fcrkiye",
        "flag_url": "//upload.wikimedia.org/wikipedia/commons/b/b4/Flag_of_Turkey.svg",
        "license": "Public domain",
        "continent": "Europe"
    },
    {
        "url": "/wiki/Turkmenistan",
        "alpha3": "TKM",
        "name": "Turkmenistan",
        "flag_url": "//upload.wikimedia.org/wikipedia/commons/1/1b/Flag_of_Turkmenistan.svg",
        "license": "Public domain",
        "continent": "Asia"
    },
    {
        "url": "/wiki/Turks_and_Caicos_Islands",
        "alpha3": "TCA",
        "name": "Turks and Caicos Islands",
        "flag_url": "//upload.wikimedia.org/wikipedia/commons/a/a0/Flag_of_the_Turks_and_Caicos_Islands.svg",
        "license": "Public domain",
        "continent": "North America"
    },
    {
        "url": "/wiki/Tuvalu",
        "alpha3": "TUV",
        "name": "Tuvalu",
        "flag_url": "//upload.wikimedia.org/wikipedia/commons/3/38/Flag_of_Tuvalu.svg",
        "license": "Public domain",
        "continent": "Oceania"
    },
    {
        "url": "/wiki/Uganda",
        "alpha3": "UGA",
        "name": "Uganda",
        "flag_url": "//upload.wikimedia.org/wikipedia/commons/4/4e/Flag_of_Uganda.svg",
        "license": "Public domain",
        "continent": "Africa"
    },
    {
        "url": "/wiki/Ukraine",
        "alpha3": "UKR",
        "name": "Ukraine",
        "flag_url": "//upload.wikimedia.org/wikipedia/commons/4/49/Flag_of_Ukraine.svg",
        "license": "Public domain",
        "continent": "Europe"
    },
    {
        "url": "/wiki/United_Arab_Emirates",
        "alpha3": "ARE",
        "name": "United Arab Emirates",
        "flag_url": "//upload.wikimedia.org/wikipedia/commons/c/cb/Flag_of_the_United_Arab_Emirates.svg",
        "license": "Public domain",
        "continent": "Asia"
    },
    {
        "url": "/wiki/United_Kingdom",
        "alpha3": "GBR",
        "name": "United Kingdom of Great Britain and Northern Ireland",
        "flag_url": "//upload.wikimedia.org/wikipedia/en/a/ae/Flag_of_the_United_Kingdom.svg",
        "license": "Public domain",
        "continent": "Europe"
    },
    {
        "url": "/wiki/United_States",
        "alpha3": "USA",
        "name": "United States of America",
        "flag_url": "//upload.wikimedia.org/wikipedia/en/a/a4/Flag_of_the_United_States.svg",
        "license": "Public domain",
        "continent": "North America"
    },
    {
        "url": "/wiki/United_States_Minor_Outlying_Islands",
        "alpha3": "UMI",
        "name": "United States Minor Outlying Islands",
        "flag_url": "//upload.wikimedia.org/wikipedia/en/a/a4/Flag_of_the_United_States.svg",
        "license": "Public domain",
        "continent": "North America"
    },
    {
        "url": "/wiki/Uruguay",
        "alpha3": "URY",
        "name": "Uruguay",
        "flag_url": "//upload.wikimedia.org/wikipedia/commons/f/fe/Flag_of_Uruguay.svg",
        "license": "Public domain",
        "continent": "South America"
    },
    {
        "url": "/wiki/Uzbekistan",
        "alpha3": "UZB",
        "name": "Uzbekistan",
        "flag_url": "//upload.wikimedia.org/wikipedia/commons/8/84/Flag_of_Uzbekistan.svg",
        "license": "Public domain",
        "continent": "Asia"
    },
    {
        "url": "/wiki/Vanuatu",
        "alpha3": "VUT",
        "name": "Vanuatu",
        "flag_url": "//upload.wikimedia.org/wikipedia/commons/6/6e/Flag_of_Vanuatu_%28official%29.svg",
        "license": "Public domain",
        "continent": "Oceania"
    },
    {
        "url": "/wiki/Venezuela",
        "alpha3": "VEN",
        "name": "Venezuela (Bolivarian Republic of)",
        "flag_url": "//upload.wikimedia.org/wikipedia/commons/0/06/Flag_of_Venezuela.svg",
        "license": "Public domain",
        "continent": "South America"
    },
    {
        "url": "/wiki/Vietnam",
        "alpha3": "VNM",
        "name": "Vietnam",
        "flag_url": "//upload.wikimedia.org/wikipedia/commons/2/21/Flag_of_Vietnam.svg",
        "license": "Public domain",
        "continent": "Asia"
    },
    {
        "url": "/wiki/British_Virgin_Islands",
        "alpha3": "VGB",
        "name": "Virgin Islands (British)",
        "flag_url": "//upload.wikimedia.org/wikipedia/commons/4/42/Flag_of_the_British_Virgin_Islands.svg",
        "license": "Public domain",
        "continent": "North America"
    },
    {
        "url": "/wiki/United_States_Virgin_Islands",
        "alpha3": "VIR",
        "name": "Virgin Islands (U.S.)",
        "flag_url": "//upload.wikimedia.org/wikipedia/commons/f/f8/Flag_of_the_United_States_Virgin_Islands.svg",
        "license": "Public domain",
        "continent": "North America"
    },
    {
        "url": "/wiki/Wallis_and_Futuna",
        "alpha3": "WLF",
        "name": "Wallis and Futuna",
        "flag_url": "//upload.wikimedia.org/wikipedia/en/c/c3/Flag_of_France.svg",
        "license": "Public domain",
        "continent": "Oceania"
    },
    {
        "url": "/wiki/Yemen",
        "alpha3": "YEM",
        "name": "Yemen",
        "flag_url": "//upload.wikimedia.org/wikipedia/commons/8/89/Flag_of_Yemen.svg",
        "license": "Public domain",
        "continent": "Asia"
    },
    {
        "url": "/wiki/Zambia",
        "alpha3": "ZMB",
        "name": "Zambia",
        "flag_url": "//upload.wikimedia.org/wikipedia/commons/0/06/Flag_of_Zambia.svg",
        "license": "Public domain",
        "continent": "Africa"
    },
    {
        "url": "/wiki/Zimbabwe",
        "alpha3": "ZWE",
        "name": "Zimbabwe",
        "flag_url": "//upload.wikimedia.org/wikipedia/commons/6/6a/Flag_of_Zimbabwe.svg",
        "license": "Public domain",
        "continent": "Africa"
    }
]
